[
  {
    "trend_arrow": "FLAT", 
    "system_time": "2016-01-19T02:29:31", 
    "display_time": "2016-01-18T22:31:17", 
    "glucose": 173
  }, 
  {
    "trend_arrow": "FLAT", 
    "system_time": "2016-01-19T02:24:31", 
    "display_time": "2016-01-18T22:26:17", 
    "glucose": 175
  }, 
  {
    "trend_arrow": "FLAT", 
    "system_time": "2016-01-19T02:19:31", 
    "display_time": "2016-01-18T22:21:17", 
    "glucose": 174
  }, 
  {
    "trend_arrow": "FLAT", 
    "system_time": "2016-01-19T02:14:31", 
    "display_time": "2016-01-18T22:16:17", 
    "glucose": 173
  }, 
  {
    "trend_arrow": "FLAT", 
    "system_time": "2016-01-19T02:09:31", 
    "display_time": "2016-01-18T22:11:17", 
    "glucose": 172
  }
]